LICENSE.txt
MANIFEST.in
README.rst
setup.cfg
setup.py
version.txt
docs/AUTHORS.txt
docs/HISTORY.rst
docs/INSTALL.rst
docs/LICENSE.GPL
vnccollab/__init__.py
vnccollab.common.egg-info/PKG-INFO
vnccollab.common.egg-info/SOURCES.txt
vnccollab.common.egg-info/dependency_links.txt
vnccollab.common.egg-info/namespace_packages.txt
vnccollab.common.egg-info/not-zip-safe
vnccollab.common.egg-info/requires.txt
vnccollab.common.egg-info/top_level.txt
vnccollab/common/__init__.py
vnccollab/common/cache.py
vnccollab/common/configure.zcml
vnccollab/common/interfaces.py
vnccollab/common/livesearch.py
vnccollab/common/searchutil.py
vnccollab/common/testing.py
vnccollab/common/util.py
vnccollab/common/vocabularies.py
vnccollab/common/browser/__init__.py
vnccollab/common/browser/configure.zcml
vnccollab/common/browser/deferred.py
vnccollab/common/browser/search.py
vnccollab/common/browser/css/main.css
vnccollab/common/browser/css/ui.dynatree.css
vnccollab/common/browser/images/reload.png
vnccollab/common/browser/images/small_rarrow.png
vnccollab/common/browser/images/spinner_arrows.gif
vnccollab/common/browser/images/spinner_arrows_nav.gif
vnccollab/common/browser/images/dynatree/icons-rtl.gif
vnccollab/common/browser/images/dynatree/icons.gif
vnccollab/common/browser/images/dynatree/loading.gif
vnccollab/common/browser/images/dynatree/vline-rtl.gif
vnccollab/common/browser/images/dynatree/vline.gif
vnccollab/common/browser/js/diff_match_patch.js
vnccollab/common/browser/js/jquery.ba-dotimeout.min.js
vnccollab/common/browser/js/jquery.dynatree.min.js
vnccollab/common/browser/js/jquery.field_selection.js
vnccollab/common/browser/js/jquery.gritter.min.js
vnccollab/common/browser/js/main.js
vnccollab/common/browser/js/slimScroll.js
vnccollab/common/browser/templates/search.pt
vnccollab/common/browser/templates/updated_search.pt
vnccollab/common/portlets/__init__.py
vnccollab/common/portlets/configure.zcml
vnccollab/common/portlets/deferred.py
vnccollab/common/profiles/default/browserlayer.xml
vnccollab/common/profiles/default/cssregistry.xml
vnccollab/common/profiles/default/jsregistry.xml
vnccollab/common/profiles/default/metadata.xml
vnccollab/common/tests/__init__.py
vnccollab/common/tests/_test_robot.py
vnccollab/common/tests/base.py
